{
    "contributors": null,
    "coordinates": null,
    "created_at": "Thu Dec 03 03:42:39 +0000 2015",
    "entities": {
        "hashtags": [
            {
                "indices": [
                    112,
                    116
                ],
                "text": "pun"
            }
        ],
        "media": [
            {
                "display_url": "pic.twitter.com/A9ozCoAbq3",
                "expanded_url": "http://twitter.com/sseshadri3/status/672259624767098880/photo/1",
                "id": 672259510585528320,
                "id_str": "672259510585528320",
                "indices": [
                    117,
                    140
                ],
                "media_url": "http://pbs.twimg.com/media/CVRYdo1UEAASew2.jpg",
                "media_url_https": "https://pbs.twimg.com/media/CVRYdo1UEAASew2.jpg",
                "sizes": {
                    "large": {
                        "h": 768,
                        "resize": "fit",
                        "w": 1024
                    },
                    "medium": {
                        "h": 450,
                        "resize": "fit",
                        "w": 600
                    },
                    "small": {
                        "h": 255,
                        "resize": "fit",
                        "w": 340
                    },
                    "thumb": {
                        "h": 150,
                        "resize": "crop",
                        "w": 150
                    }
                },
                "type": "photo",
                "url": "https://t.co/A9ozCoAbq3"
            }
        ],
        "symbols": [],
        "urls": [],
        "user_mentions": [
            {
                "id": 13298072,
                "id_str": "13298072",
                "indices": [
                    0,
                    12
                ],
                "name": "Tesla Motors",
                "screen_name": "TeslaMotors"
            }
        ]
    },
    "favorite_count": 1,
    "favorited": false,
    "geo": null,
    "id": 672259624767098880,
    "id_str": "672259624767098880",
    "in_reply_to_screen_name": "TeslaMotors",
    "in_reply_to_status_id": null,
    "in_reply_to_status_id_str": null,
    "in_reply_to_user_id": 13298072,
    "in_reply_to_user_id_str": "13298072",
    "is_quote_status": false,
    "lang": "en",
    "metadata": {
        "iso_language_code": "en",
        "result_type": "recent"
    },
    "place": null,
    "possibly_sensitive": false,
    "retweet_count": 0,
    "retweeted": false,
    "source": "<a href=\"http://twitter.com/download/iphone\" rel=\"nofollow\">Twitter for iPhone</a>",
    "text": "@TeslaMotors I don't need insane mode in my car, when I wish to feel adrenaline rush I get on to auto rickshaws #pun https://t.co/A9ozCoAbq3",
    "truncated": false,
    "user": {
        "contributors_enabled": false,
        "created_at": "Mon Dec 08 11:04:37 +0000 2008",
        "default_profile": false,
        "default_profile_image": false,
        "description": "Head, Advanced Analytics @EAMobile, Entrepreneur, Data Scientist, Machine Learning Enthusiast, Strategist, and Philosopher",
        "entities": {
            "description": {
                "urls": []
            },
            "url": {
                "urls": [
                    {
                        "display_url": "codeofthought.com",
                        "expanded_url": "http://www.codeofthought.com",
                        "indices": [
                            0,
                            23
                        ],
                        "url": "https://t.co/MhLiG8lTsw"
                    }
                ]
            }
        },
        "favourites_count": 301,
        "follow_request_sent": false,
        "followers_count": 1620,
        "following": false,
        "friends_count": 239,
        "geo_enabled": true,
        "has_extended_profile": false,
        "id": 17960624,
        "id_str": "17960624",
        "is_translation_enabled": false,
        "is_translator": false,
        "lang": "en",
        "listed_count": 21,
        "location": "US",
        "name": "Sridhar Seshadri",
        "notifications": false,
        "profile_background_color": "000000",
        "profile_background_image_url": "http://abs.twimg.com/images/themes/theme1/bg.png",
        "profile_background_image_url_https": "https://abs.twimg.com/images/themes/theme1/bg.png",
        "profile_background_tile": false,
        "profile_banner_url": "https://pbs.twimg.com/profile_banners/17960624/1438186765",
        "profile_image_url": "http://pbs.twimg.com/profile_images/626426612901220353/0jE-PMc3_normal.jpg",
        "profile_image_url_https": "https://pbs.twimg.com/profile_images/626426612901220353/0jE-PMc3_normal.jpg",
        "profile_link_color": "94D487",
        "profile_sidebar_border_color": "000000",
        "profile_sidebar_fill_color": "000000",
        "profile_text_color": "000000",
        "profile_use_background_image": false,
        "protected": false,
        "screen_name": "sseshadri3",
        "statuses_count": 2049,
        "time_zone": "New Delhi",
        "url": "https://t.co/MhLiG8lTsw",
        "utc_offset": 19800,
        "verified": false
    }
}