{
    "contributors": null,
    "coordinates": null,
    "created_at": "Tue Dec 01 13:20:38 +0000 2015",
    "entities": {
        "hashtags": [],
        "symbols": [],
        "urls": [],
        "user_mentions": [
            {
                "id": 430158505,
                "id_str": "430158505",
                "indices": [
                    0,
                    8
                ],
                "name": "Ask eBay",
                "screen_name": "AskeBay"
            }
        ]
    },
    "favorite_count": 0,
    "favorited": false,
    "geo": null,
    "id": 671680303711277056,
    "id_str": "671680303711277056",
    "in_reply_to_screen_name": "AskeBay",
    "in_reply_to_status_id": null,
    "in_reply_to_status_id_str": null,
    "in_reply_to_user_id": 430158505,
    "in_reply_to_user_id_str": "430158505",
    "is_quote_status": false,
    "lang": "en",
    "metadata": {
        "iso_language_code": "en",
        "result_type": "recent"
    },
    "place": null,
    "retweet_count": 0,
    "retweeted": false,
    "source": "<a href=\"http://twitter.com/download/iphone\" rel=\"nofollow\">Twitter for iPhone</a>",
    "text": "@AskeBay thank you for the quickest help when I needed you to step in. Great service \ud83d\udc4f\ud83c\udffc",
    "truncated": false,
    "user": {
        "contributors_enabled": false,
        "created_at": "Wed Jan 11 16:12:08 +0000 2012",
        "default_profile": false,
        "default_profile_image": false,
        "description": "English Language undergrad",
        "entities": {
            "description": {
                "urls": []
            }
        },
        "favourites_count": 3651,
        "follow_request_sent": false,
        "followers_count": 268,
        "following": false,
        "friends_count": 121,
        "geo_enabled": false,
        "has_extended_profile": false,
        "id": 461248061,
        "id_str": "461248061",
        "is_translation_enabled": false,
        "is_translator": false,
        "lang": "en",
        "listed_count": 2,
        "location": "",
        "name": "Stephanie Lukins",
        "notifications": false,
        "profile_background_color": "ACDED6",
        "profile_background_image_url": "http://pbs.twimg.com/profile_background_images/509071723631607808/Fmq17i1D.jpeg",
        "profile_background_image_url_https": "https://pbs.twimg.com/profile_background_images/509071723631607808/Fmq17i1D.jpeg",
        "profile_background_tile": true,
        "profile_banner_url": "https://pbs.twimg.com/profile_banners/461248061/1448883246",
        "profile_image_url": "http://pbs.twimg.com/profile_images/658065484949147648/nSgDaqxm_normal.jpg",
        "profile_image_url_https": "https://pbs.twimg.com/profile_images/658065484949147648/nSgDaqxm_normal.jpg",
        "profile_link_color": "038543",
        "profile_sidebar_border_color": "000000",
        "profile_sidebar_fill_color": "F6F6F6",
        "profile_text_color": "333333",
        "profile_use_background_image": true,
        "protected": false,
        "screen_name": "stephanielukins",
        "statuses_count": 11329,
        "time_zone": "London",
        "url": null,
        "utc_offset": 0,
        "verified": false
    }
}