{
    "contributors": null,
    "coordinates": null,
    "created_at": "Tue Dec 08 19:59:16 +0000 2015",
    "entities": {
        "hashtags": [],
        "symbols": [],
        "urls": [],
        "user_mentions": [
            {
                "id": 20793816,
                "id_str": "20793816",
                "indices": [
                    0,
                    7
                ],
                "name": "Amazon",
                "screen_name": "amazon"
            },
            {
                "id": 17220817,
                "id_str": "17220817",
                "indices": [
                    8,
                    20
                ],
                "name": "Amazon Video",
                "screen_name": "AmazonVideo"
            }
        ]
    },
    "favorite_count": 0,
    "favorited": false,
    "geo": null,
    "id": 674317339794477056,
    "id_str": "674317339794477056",
    "in_reply_to_screen_name": "amazon",
    "in_reply_to_status_id": null,
    "in_reply_to_status_id_str": null,
    "in_reply_to_user_id": 20793816,
    "in_reply_to_user_id_str": "20793816",
    "is_quote_status": false,
    "lang": "en",
    "metadata": {
        "iso_language_code": "en",
        "result_type": "recent"
    },
    "place": null,
    "retweet_count": 0,
    "retweeted": false,
    "source": "<a href=\"http://twitter.com/download/android\" rel=\"nofollow\">Twitter for Android</a>",
    "text": "@amazon @AmazonVideo Yall added Starz &amp; Showtime? I swear if I never told yall I love you, I mean it now",
    "truncated": false,
    "user": {
        "contributors_enabled": false,
        "created_at": "Tue Aug 30 09:24:25 +0000 2011",
        "default_profile": true,
        "default_profile_image": false,
        "description": "I'm writing a diss mixtape over one long ass beat for the niggas that wouldn't let me out early. #30Nights #CudFam #Lakers #FreeSaintStephan",
        "entities": {
            "description": {
                "urls": []
            },
            "url": {
                "urls": [
                    {
                        "display_url": "FreeStStephan.com/YoMomThrowingI\u2026",
                        "expanded_url": "http://www.FreeStStephan.com/YoMomThrowingItBack",
                        "indices": [
                            0,
                            23
                        ],
                        "url": "https://t.co/kedwj0AFDt"
                    }
                ]
            }
        },
        "favourites_count": 1755,
        "follow_request_sent": false,
        "followers_count": 2014,
        "following": false,
        "friends_count": 2091,
        "geo_enabled": true,
        "has_extended_profile": true,
        "id": 364769778,
        "id_str": "364769778",
        "is_translation_enabled": false,
        "is_translator": false,
        "lang": "en",
        "listed_count": 45,
        "location": "Miami, FL",
        "name": "Rich Homie Steph",
        "notifications": false,
        "profile_background_color": "C0DEED",
        "profile_background_image_url": "http://abs.twimg.com/images/themes/theme1/bg.png",
        "profile_background_image_url_https": "https://abs.twimg.com/images/themes/theme1/bg.png",
        "profile_background_tile": false,
        "profile_banner_url": "https://pbs.twimg.com/profile_banners/364769778/1426668944",
        "profile_image_url": "http://pbs.twimg.com/profile_images/669244991894630400/BfSHVP9C_normal.jpg",
        "profile_image_url_https": "https://pbs.twimg.com/profile_images/669244991894630400/BfSHVP9C_normal.jpg",
        "profile_link_color": "0084B4",
        "profile_sidebar_border_color": "C0DEED",
        "profile_sidebar_fill_color": "DDEEF6",
        "profile_text_color": "333333",
        "profile_use_background_image": true,
        "protected": false,
        "screen_name": "Saint_Stephan",
        "statuses_count": 147289,
        "time_zone": "Eastern Time (US & Canada)",
        "url": "https://t.co/kedwj0AFDt",
        "utc_offset": -18000,
        "verified": false
    }
}