{
    "contributors": null,
    "coordinates": null,
    "created_at": "Tue Dec 01 21:15:54 +0000 2015",
    "entities": {
        "hashtags": [],
        "symbols": [],
        "urls": [],
        "user_mentions": [
            {
                "id": 59889953,
                "id_str": "59889953",
                "indices": [
                    0,
                    8
                ],
                "name": "Verizon",
                "screen_name": "verizon"
            }
        ]
    },
    "favorite_count": 0,
    "favorited": false,
    "geo": null,
    "id": 671799908609970176,
    "id_str": "671799908609970176",
    "in_reply_to_screen_name": "verizon",
    "in_reply_to_status_id": 671796538331541505,
    "in_reply_to_status_id_str": "671796538331541505",
    "in_reply_to_user_id": 59889953,
    "in_reply_to_user_id_str": "59889953",
    "is_quote_status": false,
    "lang": "en",
    "metadata": {
        "iso_language_code": "en",
        "result_type": "recent"
    },
    "place": null,
    "retweet_count": 0,
    "retweeted": false,
    "source": "<a href=\"http://twitter.com\" rel=\"nofollow\">Twitter Web Client</a>",
    "text": "@verizon Dang it, T-Mobile stepped up a few hours ago.  Thank you for reaching out, will remember next time!",
    "truncated": false,
    "user": {
        "contributors_enabled": false,
        "created_at": "Sun Apr 19 00:24:35 +0000 2009",
        "default_profile": true,
        "default_profile_image": false,
        "description": "Haley and Doodle's Mom",
        "entities": {
            "description": {
                "urls": []
            },
            "url": {
                "urls": [
                    {
                        "display_url": "keywestkey.com",
                        "expanded_url": "http://www.keywestkey.com",
                        "indices": [
                            0,
                            22
                        ],
                        "url": "http://t.co/YnKg4fUxXy"
                    }
                ]
            }
        },
        "favourites_count": 42,
        "follow_request_sent": false,
        "followers_count": 428,
        "following": false,
        "friends_count": 203,
        "geo_enabled": false,
        "has_extended_profile": false,
        "id": 33064799,
        "id_str": "33064799",
        "is_translation_enabled": false,
        "is_translator": false,
        "lang": "en",
        "listed_count": 13,
        "location": "Key West Florida 33040",
        "name": "Susie Key West",
        "notifications": false,
        "profile_background_color": "C0DEED",
        "profile_background_image_url": "http://abs.twimg.com/images/themes/theme1/bg.png",
        "profile_background_image_url_https": "https://abs.twimg.com/images/themes/theme1/bg.png",
        "profile_background_tile": false,
        "profile_banner_url": "https://pbs.twimg.com/profile_banners/33064799/1431899182",
        "profile_image_url": "http://pbs.twimg.com/profile_images/2446999993/4enthh1avclgs9dxcan5_normal.jpeg",
        "profile_image_url_https": "https://pbs.twimg.com/profile_images/2446999993/4enthh1avclgs9dxcan5_normal.jpeg",
        "profile_link_color": "0084B4",
        "profile_sidebar_border_color": "C0DEED",
        "profile_sidebar_fill_color": "DDEEF6",
        "profile_text_color": "333333",
        "profile_use_background_image": true,
        "protected": false,
        "screen_name": "susiekwest",
        "statuses_count": 584,
        "time_zone": "Quito",
        "url": "http://t.co/YnKg4fUxXy",
        "utc_offset": -18000,
        "verified": false
    }
}