{
    "contributors": null,
    "coordinates": null,
    "created_at": "Mon Dec 07 11:59:39 +0000 2015",
    "entities": {
        "hashtags": [],
        "symbols": [],
        "urls": [
            {
                "display_url": "direct.asda.com/Homemaker-Natu\u2026",
                "expanded_url": "http://direct.asda.com/Homemaker-Natural-Stag-Rug/002032327,default,pd.html?cgid=D26M01G01C12",
                "indices": [
                    111,
                    134
                ],
                "url": "https://t.co/fiFVV6ye89"
            }
        ],
        "user_mentions": [
            {
                "id": 378623571,
                "id_str": "378623571",
                "indices": [
                    0,
                    16
                ],
                "name": "Asda Service Team",
                "screen_name": "AsdaServiceTeam"
            }
        ]
    },
    "favorite_count": 0,
    "favorited": false,
    "geo": null,
    "id": 673834252534960128,
    "id_str": "673834252534960128",
    "in_reply_to_screen_name": "AsdaServiceTeam",
    "in_reply_to_status_id": null,
    "in_reply_to_status_id_str": null,
    "in_reply_to_user_id": 378623571,
    "in_reply_to_user_id_str": "378623571",
    "is_quote_status": false,
    "lang": "en",
    "metadata": {
        "iso_language_code": "en",
        "result_type": "recent"
    },
    "place": null,
    "possibly_sensitive": false,
    "retweet_count": 0,
    "retweeted": false,
    "source": "<a href=\"http://twitter.com\" rel=\"nofollow\">Twitter Web Client</a>",
    "text": "@AsdaServiceTeam Tried to purchase this rug below to N.Ireland but it keeps coming up delivery is unavailable? https://t.co/fiFVV6ye89",
    "truncated": false,
    "user": {
        "contributors_enabled": false,
        "created_at": "Tue Jun 16 02:31:39 +0000 2009",
        "default_profile": false,
        "default_profile_image": false,
        "description": "#Freelance Digital #Marketer, doing all of the things, and some of the stuffs! On the board of @niscifest & @bytenight. Generally #sunnysideup",
        "entities": {
            "description": {
                "urls": []
            },
            "url": {
                "urls": [
                    {
                        "display_url": "emmaleahy.com",
                        "expanded_url": "http://www.emmaleahy.com",
                        "indices": [
                            0,
                            23
                        ],
                        "url": "https://t.co/C6fBNFMRB5"
                    }
                ]
            }
        },
        "favourites_count": 1207,
        "follow_request_sent": false,
        "followers_count": 547,
        "following": false,
        "friends_count": 435,
        "geo_enabled": true,
        "has_extended_profile": false,
        "id": 47518479,
        "id_str": "47518479",
        "is_translation_enabled": false,
        "is_translator": false,
        "lang": "en",
        "listed_count": 27,
        "location": "Belfast",
        "name": "Emma Leahy",
        "notifications": false,
        "profile_background_color": "C6E2EE",
        "profile_background_image_url": "http://abs.twimg.com/images/themes/theme2/bg.gif",
        "profile_background_image_url_https": "https://abs.twimg.com/images/themes/theme2/bg.gif",
        "profile_background_tile": false,
        "profile_banner_url": "https://pbs.twimg.com/profile_banners/47518479/1446816183",
        "profile_image_url": "http://pbs.twimg.com/profile_images/587572606108336128/O_fV-PkD_normal.jpg",
        "profile_image_url_https": "https://pbs.twimg.com/profile_images/587572606108336128/O_fV-PkD_normal.jpg",
        "profile_link_color": "1F98C7",
        "profile_sidebar_border_color": "C6E2EE",
        "profile_sidebar_fill_color": "DAECF4",
        "profile_text_color": "663B12",
        "profile_use_background_image": true,
        "protected": false,
        "screen_name": "emsiememsie",
        "statuses_count": 3898,
        "time_zone": "Casablanca",
        "url": "https://t.co/C6fBNFMRB5",
        "utc_offset": 0,
        "verified": false
    }
}