{
    "contributors": null,
    "coordinates": null,
    "created_at": "Sun Dec 06 03:14:34 +0000 2015",
    "entities": {
        "hashtags": [],
        "symbols": [],
        "urls": [],
        "user_mentions": [
            {
                "id": 38676903,
                "id_str": "38676903",
                "indices": [
                    0,
                    8
                ],
                "name": "easyJet",
                "screen_name": "easyJet"
            }
        ]
    },
    "favorite_count": 0,
    "favorited": false,
    "geo": null,
    "id": 673339722392018946,
    "id_str": "673339722392018946",
    "in_reply_to_screen_name": "easyJet",
    "in_reply_to_status_id": 672719000623689728,
    "in_reply_to_status_id_str": "672719000623689728",
    "in_reply_to_user_id": 38676903,
    "in_reply_to_user_id_str": "38676903",
    "is_quote_status": false,
    "lang": "en",
    "metadata": {
        "iso_language_code": "en",
        "result_type": "recent"
    },
    "place": null,
    "retweet_count": 0,
    "retweeted": false,
    "source": "<a href=\"http://twitter.com/download/iphone\" rel=\"nofollow\">Twitter for iPhone</a>",
    "text": "@easyJet hiya. I updated the mobile app. My boarding passes went from section. Downloaded again and still not showing in b/p part of app",
    "truncated": false,
    "user": {
        "contributors_enabled": false,
        "created_at": "Sun Jan 29 20:09:45 +0000 2012",
        "default_profile": true,
        "default_profile_image": false,
        "description": "Love punk rock and Hibernian.",
        "entities": {
            "description": {
                "urls": []
            }
        },
        "favourites_count": 3511,
        "follow_request_sent": false,
        "followers_count": 92,
        "following": false,
        "friends_count": 336,
        "geo_enabled": true,
        "has_extended_profile": false,
        "id": 478004459,
        "id_str": "478004459",
        "is_translation_enabled": false,
        "is_translator": false,
        "lang": "en",
        "listed_count": 1,
        "location": "Lanarkshire",
        "name": "murzo",
        "notifications": false,
        "profile_background_color": "C0DEED",
        "profile_background_image_url": "http://abs.twimg.com/images/themes/theme1/bg.png",
        "profile_background_image_url_https": "https://abs.twimg.com/images/themes/theme1/bg.png",
        "profile_background_tile": false,
        "profile_image_url": "http://pbs.twimg.com/profile_images/446729495027146752/zW50zrgI_normal.jpeg",
        "profile_image_url_https": "https://pbs.twimg.com/profile_images/446729495027146752/zW50zrgI_normal.jpeg",
        "profile_link_color": "0084B4",
        "profile_sidebar_border_color": "C0DEED",
        "profile_sidebar_fill_color": "DDEEF6",
        "profile_text_color": "333333",
        "profile_use_background_image": true,
        "protected": false,
        "screen_name": "hfcpunk",
        "statuses_count": 1073,
        "time_zone": null,
        "url": null,
        "utc_offset": null,
        "verified": false
    }
}