{
    "contributors": null,
    "coordinates": null,
    "created_at": "Thu Nov 26 10:59:41 +0000 2015",
    "entities": {
        "hashtags": [],
        "symbols": [],
        "urls": [],
        "user_mentions": [
            {
                "id": 46640060,
                "id_str": "46640060",
                "indices": [
                    0,
                    12
                ],
                "name": "Halfords",
                "screen_name": "Halfords_uk"
            }
        ]
    },
    "favorite_count": 1,
    "favorited": false,
    "geo": null,
    "id": 669832894077083648,
    "id_str": "669832894077083648",
    "in_reply_to_screen_name": "Halfords_uk",
    "in_reply_to_status_id": null,
    "in_reply_to_status_id_str": null,
    "in_reply_to_user_id": 46640060,
    "in_reply_to_user_id_str": "46640060",
    "is_quote_status": false,
    "lang": "en",
    "metadata": {
        "iso_language_code": "en",
        "result_type": "recent"
    },
    "place": null,
    "retweet_count": 0,
    "retweeted": false,
    "source": "<a href=\"http://twitter.com/download/iphone\" rel=\"nofollow\">Twitter for iPhone</a>",
    "text": "@Halfords_uk fantastic service in your Dublin - Blanchardstown store",
    "truncated": false,
    "user": {
        "contributors_enabled": false,
        "created_at": "Tue Mar 15 23:13:01 +0000 2011",
        "default_profile": false,
        "default_profile_image": false,
        "description": "Uefa 'A' licenced coach played for Liverpool and Shamrock Rovers still follow both teams I like \u26bd\u26f3 love my kids MJ & Ava (all views are mine)",
        "entities": {
            "description": {
                "urls": []
            }
        },
        "favourites_count": 14037,
        "follow_request_sent": false,
        "followers_count": 1839,
        "following": false,
        "friends_count": 692,
        "geo_enabled": true,
        "has_extended_profile": false,
        "id": 266858390,
        "id_str": "266858390",
        "is_translation_enabled": false,
        "is_translator": false,
        "lang": "en",
        "listed_count": 10,
        "location": "Dublin",
        "name": "Marc Kenny",
        "notifications": false,
        "profile_background_color": "131516",
        "profile_background_image_url": "http://abs.twimg.com/images/themes/theme14/bg.gif",
        "profile_background_image_url_https": "https://abs.twimg.com/images/themes/theme14/bg.gif",
        "profile_background_tile": false,
        "profile_image_url": "http://pbs.twimg.com/profile_images/660763023867555840/gM0Q2_8b_normal.jpg",
        "profile_image_url_https": "https://pbs.twimg.com/profile_images/660763023867555840/gM0Q2_8b_normal.jpg",
        "profile_link_color": "009999",
        "profile_sidebar_border_color": "EEEEEE",
        "profile_sidebar_fill_color": "EFEFEF",
        "profile_text_color": "333333",
        "profile_use_background_image": false,
        "protected": false,
        "screen_name": "marcjohnkenny",
        "statuses_count": 14907,
        "time_zone": "Dublin",
        "url": null,
        "utc_offset": 0,
        "verified": false
    }
}