{
    "contributors": null,
    "coordinates": null,
    "created_at": "Sat Dec 05 22:28:21 +0000 2015",
    "entities": {
        "hashtags": [],
        "symbols": [],
        "urls": [],
        "user_mentions": [
            {
                "id": 86925202,
                "id_str": "86925202",
                "indices": [
                    0,
                    4
                ],
                "name": "ITV",
                "screen_name": "ITV"
            },
            {
                "id": 19370890,
                "id_str": "19370890",
                "indices": [
                    5,
                    18
                ],
                "name": "Michael Regan",
                "screen_name": "MichaelRegan"
            },
            {
                "id": 17310915,
                "id_str": "17310915",
                "indices": [
                    19,
                    32
                ],
                "name": "imacelebrity",
                "screen_name": "imacelebrity"
            }
        ]
    },
    "favorite_count": 1,
    "favorited": false,
    "geo": null,
    "id": 673267695387832321,
    "id_str": "673267695387832321",
    "in_reply_to_screen_name": "ITV",
    "in_reply_to_status_id": 673252788508360705,
    "in_reply_to_status_id_str": "673252788508360705",
    "in_reply_to_user_id": 86925202,
    "in_reply_to_user_id_str": "86925202",
    "is_quote_status": false,
    "lang": "en",
    "metadata": {
        "iso_language_code": "en",
        "result_type": "recent"
    },
    "place": null,
    "retweet_count": 0,
    "retweeted": false,
    "source": "<a href=\"http://twitter.com\" rel=\"nofollow\">Twitter Web Client</a>",
    "text": "@ITV @MichaelRegan @imacelebrity Embarrassing.....and I've done it.",
    "truncated": false,
    "user": {
        "contributors_enabled": false,
        "created_at": "Thu Jan 06 22:07:09 +0000 2011",
        "default_profile": false,
        "default_profile_image": false,
        "description": "Sports photographer for Action Images and official photographer to my children.  Views are my own and are often pointless.",
        "entities": {
            "description": {
                "urls": []
            }
        },
        "favourites_count": 3175,
        "follow_request_sent": false,
        "followers_count": 1317,
        "following": false,
        "friends_count": 257,
        "geo_enabled": true,
        "has_extended_profile": false,
        "id": 234915684,
        "id_str": "234915684",
        "is_translation_enabled": false,
        "is_translator": false,
        "lang": "en",
        "listed_count": 58,
        "location": "Newcastle-under-Lyme",
        "name": "Carl Recine",
        "notifications": false,
        "profile_background_color": "131516",
        "profile_background_image_url": "http://abs.twimg.com/images/themes/theme14/bg.gif",
        "profile_background_image_url_https": "https://abs.twimg.com/images/themes/theme14/bg.gif",
        "profile_background_tile": true,
        "profile_banner_url": "https://pbs.twimg.com/profile_banners/234915684/1429692738",
        "profile_image_url": "http://pbs.twimg.com/profile_images/584321454768021504/3qMTdPRB_normal.jpg",
        "profile_image_url_https": "https://pbs.twimg.com/profile_images/584321454768021504/3qMTdPRB_normal.jpg",
        "profile_link_color": "009999",
        "profile_sidebar_border_color": "EEEEEE",
        "profile_sidebar_fill_color": "EFEFEF",
        "profile_text_color": "333333",
        "profile_use_background_image": true,
        "protected": false,
        "screen_name": "carlrecine",
        "statuses_count": 8053,
        "time_zone": null,
        "url": null,
        "utc_offset": null,
        "verified": false
    }
}