{
    "contributors": null,
    "coordinates": null,
    "created_at": "Tue Dec 01 17:18:16 +0000 2015",
    "entities": {
        "hashtags": [],
        "symbols": [],
        "urls": [],
        "user_mentions": [
            {
                "id": 13058772,
                "id_str": "13058772",
                "indices": [
                    0,
                    9
                ],
                "name": "LinkedIn",
                "screen_name": "LinkedIn"
            }
        ]
    },
    "favorite_count": 1,
    "favorited": false,
    "geo": null,
    "id": 671740108094181380,
    "id_str": "671740108094181380",
    "in_reply_to_screen_name": "LinkedIn",
    "in_reply_to_status_id": 671739439807246336,
    "in_reply_to_status_id_str": "671739439807246336",
    "in_reply_to_user_id": 13058772,
    "in_reply_to_user_id_str": "13058772",
    "is_quote_status": false,
    "lang": "en",
    "metadata": {
        "iso_language_code": "en",
        "result_type": "recent"
    },
    "place": null,
    "retweet_count": 0,
    "retweeted": false,
    "source": "<a href=\"http://twitter.com\" rel=\"nofollow\">Twitter Web Client</a>",
    "text": "@LinkedIn Wrong culture LinkedIn. UK doesn't have office holiday parties this time of year, it has office Christmas parties.",
    "truncated": false,
    "user": {
        "contributors_enabled": false,
        "created_at": "Sat Mar 06 17:22:44 +0000 2010",
        "default_profile": false,
        "default_profile_image": false,
        "description": "'...a great gift for calming troubled unionist souls.' '...the pathologically closed mind of a British nationalist fanatic filled with mindless hate' #1599",
        "entities": {
            "description": {
                "urls": []
            },
            "url": {
                "urls": [
                    {
                        "display_url": "mercinon.wordpress.com",
                        "expanded_url": "https://mercinon.wordpress.com/",
                        "indices": [
                            0,
                            23
                        ],
                        "url": "https://t.co/8MwdS8pKRe"
                    }
                ]
            }
        },
        "favourites_count": 18946,
        "follow_request_sent": false,
        "followers_count": 1681,
        "following": false,
        "friends_count": 1338,
        "geo_enabled": true,
        "has_extended_profile": false,
        "id": 120513326,
        "id_str": "120513326",
        "is_translation_enabled": false,
        "is_translator": false,
        "lang": "en",
        "listed_count": 37,
        "location": "Aberdeen, Scotland",
        "name": "Roger White",
        "notifications": false,
        "profile_background_color": "EBEBEB",
        "profile_background_image_url": "http://abs.twimg.com/images/themes/theme7/bg.gif",
        "profile_background_image_url_https": "https://abs.twimg.com/images/themes/theme7/bg.gif",
        "profile_background_tile": false,
        "profile_banner_url": "https://pbs.twimg.com/profile_banners/120513326/1448615631",
        "profile_image_url": "http://pbs.twimg.com/profile_images/512731139367129088/Y2sYY2Et_normal.jpeg",
        "profile_image_url_https": "https://pbs.twimg.com/profile_images/512731139367129088/Y2sYY2Et_normal.jpeg",
        "profile_link_color": "990000",
        "profile_sidebar_border_color": "DFDFDF",
        "profile_sidebar_fill_color": "F3F3F3",
        "profile_text_color": "333333",
        "profile_use_background_image": true,
        "protected": false,
        "screen_name": "rogerlwhite",
        "statuses_count": 27803,
        "time_zone": "London",
        "url": "https://t.co/8MwdS8pKRe",
        "utc_offset": 0,
        "verified": false
    }
}