{
    "contributors": null,
    "coordinates": null,
    "created_at": "Mon Nov 30 23:55:27 +0000 2015",
    "entities": {
        "hashtags": [],
        "symbols": [],
        "urls": [
            {
                "display_url": "amp.twimg.com/v/1a938569-82a\u2026",
                "expanded_url": "https://amp.twimg.com/v/1a938569-82af-4138-b475-70a2a20630ee",
                "indices": [
                    105,
                    128
                ],
                "url": "https://t.co/7k4Ur1qDUy"
            }
        ],
        "user_mentions": [
            {
                "id": 47459700,
                "id_str": "47459700",
                "indices": [
                    0,
                    9
                ],
                "name": "Burberry",
                "screen_name": "Burberry"
            },
            {
                "id": 47459700,
                "id_str": "47459700",
                "indices": [
                    26,
                    35
                ],
                "name": "Burberry",
                "screen_name": "Burberry"
            },
            {
                "id": 174593833,
                "id_str": "174593833",
                "indices": [
                    89,
                    103
                ],
                "name": "Elton John",
                "screen_name": "eltonofficial"
            }
        ]
    },
    "favorite_count": 0,
    "favorited": false,
    "geo": null,
    "id": 671477673659662338,
    "id_str": "671477673659662338",
    "in_reply_to_screen_name": "Burberry",
    "in_reply_to_status_id": null,
    "in_reply_to_status_id_str": null,
    "in_reply_to_user_id": 47459700,
    "in_reply_to_user_id_str": "47459700",
    "is_quote_status": false,
    "lang": "en",
    "metadata": {
        "iso_language_code": "en",
        "result_type": "recent"
    },
    "place": null,
    "possibly_sensitive": false,
    "retweet_count": 0,
    "retweeted": false,
    "source": "<a href=\"http://twitter.com/download/android\" rel=\"nofollow\">Twitter for Android</a>",
    "text": "@Burberry Introducing the @Burberry\nfestive film, starring an all-British cast including @EltonOfficial.\nhttps://t.co/7k4Ur1qDUy",
    "truncated": false,
    "user": {
        "contributors_enabled": false,
        "created_at": "Sat Sep 19 00:29:16 +0000 2015",
        "default_profile": false,
        "default_profile_image": false,
        "description": "Confira atualiza\u00e7\u00f5es di\u00e1rias na maior fonte de not\u00edcias de Justin Bieber da Am\u00e9rica Latina.Acesse https://t.co/7s7NIeIsOI",
        "entities": {
            "description": {
                "urls": [
                    {
                        "display_url": "lojabm.com",
                        "expanded_url": "http://lojabm.com",
                        "indices": [
                            98,
                            121
                        ],
                        "url": "https://t.co/7s7NIeIsOI"
                    }
                ]
            },
            "url": {
                "urls": [
                    {
                        "display_url": "biebermania.com.br",
                        "expanded_url": "http://biebermania.com.br",
                        "indices": [
                            0,
                            23
                        ],
                        "url": "https://t.co/t4RiSCj5jV"
                    }
                ]
            }
        },
        "favourites_count": 1194,
        "follow_request_sent": false,
        "followers_count": 3870,
        "following": false,
        "friends_count": 2661,
        "geo_enabled": false,
        "has_extended_profile": false,
        "id": 3701735957,
        "id_str": "3701735957",
        "is_translation_enabled": false,
        "is_translator": false,
        "lang": "pt",
        "listed_count": 11,
        "location": "equipebmbr@gmail.com",
        "name": "Bieber Mania Brasil",
        "notifications": false,
        "profile_background_color": "000000",
        "profile_background_image_url": "http://abs.twimg.com/images/themes/theme1/bg.png",
        "profile_background_image_url_https": "https://abs.twimg.com/images/themes/theme1/bg.png",
        "profile_background_tile": false,
        "profile_banner_url": "https://pbs.twimg.com/profile_banners/3701735957/1449441799",
        "profile_image_url": "http://pbs.twimg.com/profile_images/673633850988343297/cq6nZiOM_normal.jpg",
        "profile_image_url_https": "https://pbs.twimg.com/profile_images/673633850988343297/cq6nZiOM_normal.jpg",
        "profile_link_color": "89C9FA",
        "profile_sidebar_border_color": "000000",
        "profile_sidebar_fill_color": "000000",
        "profile_text_color": "000000",
        "profile_use_background_image": false,
        "protected": false,
        "screen_name": "Biebersmaniabrr",
        "statuses_count": 6468,
        "time_zone": "Pacific Time (US & Canada)",
        "url": "https://t.co/t4RiSCj5jV",
        "utc_offset": -28800,
        "verified": false
    }
}