{
    "contributors": null,
    "coordinates": null,
    "created_at": "Mon Dec 07 10:10:59 +0000 2015",
    "entities": {
        "hashtags": [
            {
                "indices": [
                    49,
                    65
                ],
                "text": "beautycosmetics"
            },
            {
                "indices": [
                    66,
                    84
                ],
                "text": "theartofchristmas"
            }
        ],
        "media": [
            {
                "display_url": "pic.twitter.com/x31nXkfgpm",
                "expanded_url": "http://twitter.com/ashleeehowe/status/673806904234254337/video/1",
                "id": 673806793148112896,
                "id_str": "673806793148112896",
                "indices": [
                    85,
                    108
                ],
                "media_url": "http://pbs.twimg.com/ext_tw_video_thumb/673806793148112896/pu/img/IRXaGnGi49fokDVJ.jpg",
                "media_url_https": "https://pbs.twimg.com/ext_tw_video_thumb/673806793148112896/pu/img/IRXaGnGi49fokDVJ.jpg",
                "sizes": {
                    "large": {
                        "h": 672,
                        "resize": "fit",
                        "w": 384
                    },
                    "medium": {
                        "h": 672,
                        "resize": "fit",
                        "w": 384
                    },
                    "small": {
                        "h": 595,
                        "resize": "fit",
                        "w": 340
                    },
                    "thumb": {
                        "h": 150,
                        "resize": "crop",
                        "w": 150
                    }
                },
                "type": "photo",
                "url": "https://t.co/x31nXkfgpm"
            }
        ],
        "symbols": [],
        "urls": [],
        "user_mentions": [
            {
                "id": 37916167,
                "id_str": "37916167",
                "indices": [
                    0,
                    16
                ],
                "name": "M&S",
                "screen_name": "marksandspencer"
            }
        ]
    },
    "favorite_count": 0,
    "favorited": false,
    "geo": null,
    "id": 673806904234254337,
    "id_str": "673806904234254337",
    "in_reply_to_screen_name": "marksandspencer",
    "in_reply_to_status_id": null,
    "in_reply_to_status_id_str": null,
    "in_reply_to_user_id": 37916167,
    "in_reply_to_user_id_str": "37916167",
    "is_quote_status": false,
    "lang": "en",
    "metadata": {
        "iso_language_code": "en",
        "result_type": "recent"
    },
    "place": null,
    "possibly_sensitive": false,
    "retweet_count": 0,
    "retweeted": false,
    "source": "<a href=\"http://twitter.com/download/iphone\" rel=\"nofollow\">Twitter for iPhone</a>",
    "text": "@marksandspencer advent calendar is my world\u2764\ufe0f\ud83d\udc85\ud83c\udffc #beautycosmetics #theartofchristmas https://t.co/x31nXkfgpm",
    "truncated": false,
    "user": {
        "contributors_enabled": false,
        "created_at": "Wed Dec 08 15:22:43 +0000 2010",
        "default_profile": false,
        "default_profile_image": false,
        "description": "Gym enthusiast || beauty addict",
        "entities": {
            "description": {
                "urls": []
            }
        },
        "favourites_count": 1990,
        "follow_request_sent": false,
        "followers_count": 212,
        "following": false,
        "friends_count": 269,
        "geo_enabled": true,
        "has_extended_profile": true,
        "id": 224261858,
        "id_str": "224261858",
        "is_translation_enabled": false,
        "is_translator": false,
        "lang": "en",
        "listed_count": 1,
        "location": "York -England ",
        "name": "Ashleigh",
        "notifications": false,
        "profile_background_color": "FFFAFC",
        "profile_background_image_url": "http://pbs.twimg.com/profile_background_images/495253227302961152/yiK4uO0r.jpeg",
        "profile_background_image_url_https": "https://pbs.twimg.com/profile_background_images/495253227302961152/yiK4uO0r.jpeg",
        "profile_background_tile": true,
        "profile_banner_url": "https://pbs.twimg.com/profile_banners/224261858/1406912310",
        "profile_image_url": "http://pbs.twimg.com/profile_images/658673570504167424/BIVu1-yy_normal.jpg",
        "profile_image_url_https": "https://pbs.twimg.com/profile_images/658673570504167424/BIVu1-yy_normal.jpg",
        "profile_link_color": "FA87A8",
        "profile_sidebar_border_color": "FFFFFF",
        "profile_sidebar_fill_color": "FAEBFA",
        "profile_text_color": "2E2D2E",
        "profile_use_background_image": false,
        "protected": false,
        "screen_name": "ashleeehowe",
        "statuses_count": 4418,
        "time_zone": "London",
        "url": null,
        "utc_offset": 0,
        "verified": false
    }
}