{
    "contributors": null,
    "coordinates": null,
    "created_at": "Fri Dec 04 15:55:37 +0000 2015",
    "entities": {
        "hashtags": [],
        "symbols": [],
        "urls": [
            {
                "display_url": "commun.it",
                "expanded_url": "http://commun.it",
                "indices": [
                    66,
                    89
                ],
                "url": "https://t.co/aJ69et5XyG"
            }
        ],
        "user_mentions": [
            {
                "id": 20123366,
                "id_str": "20123366",
                "indices": [
                    0,
                    5
                ],
                "name": "Asda",
                "screen_name": "asda"
            }
        ]
    },
    "favorite_count": 0,
    "favorited": false,
    "geo": null,
    "id": 672806472548524032,
    "id_str": "672806472548524032",
    "in_reply_to_screen_name": "asda",
    "in_reply_to_status_id": 672392375675674625,
    "in_reply_to_status_id_str": "672392375675674625",
    "in_reply_to_user_id": 20123366,
    "in_reply_to_user_id_str": "20123366",
    "is_quote_status": false,
    "lang": "en",
    "metadata": {
        "iso_language_code": "en",
        "result_type": "recent"
    },
    "place": null,
    "possibly_sensitive": false,
    "retweet_count": 0,
    "retweeted": false,
    "source": "<a href=\"https://commun.it\" rel=\"nofollow\">Commun.it</a>",
    "text": "@asda thanks for sharing Asda, have a great Friday :) (insight by https://t.co/aJ69et5XyG)",
    "truncated": false,
    "user": {
        "contributors_enabled": false,
        "created_at": "Fri Jul 24 10:22:25 +0000 2015",
        "default_profile": false,
        "default_profile_image": false,
        "description": "Sonny's Caf\u00e9 - Newly opened - The perfect place for delicious homemade breakfasts, lunches & light bites in Hull. We also do coffees to go! \u2615",
        "entities": {
            "description": {
                "urls": []
            }
        },
        "favourites_count": 88,
        "follow_request_sent": false,
        "followers_count": 403,
        "following": false,
        "friends_count": 607,
        "geo_enabled": false,
        "has_extended_profile": false,
        "id": 3390773207,
        "id_str": "3390773207",
        "is_translation_enabled": false,
        "is_translator": false,
        "lang": "en",
        "listed_count": 58,
        "location": "28 Caroline Street, Hull",
        "name": "Sonny's Cafe Hull",
        "notifications": false,
        "profile_background_color": "131516",
        "profile_background_image_url": "http://abs.twimg.com/images/themes/theme14/bg.gif",
        "profile_background_image_url_https": "https://abs.twimg.com/images/themes/theme14/bg.gif",
        "profile_background_tile": true,
        "profile_banner_url": "https://pbs.twimg.com/profile_banners/3390773207/1447683898",
        "profile_image_url": "http://pbs.twimg.com/profile_images/662637734251659264/nmT4ZJsT_normal.jpg",
        "profile_image_url_https": "https://pbs.twimg.com/profile_images/662637734251659264/nmT4ZJsT_normal.jpg",
        "profile_link_color": "FA743E",
        "profile_sidebar_border_color": "000000",
        "profile_sidebar_fill_color": "000000",
        "profile_text_color": "000000",
        "profile_use_background_image": true,
        "protected": false,
        "screen_name": "SonnysCafeHull",
        "statuses_count": 3488,
        "time_zone": "London",
        "url": null,
        "utc_offset": 0,
        "verified": false
    }
}