{
    "contributors": null,
    "coordinates": null,
    "created_at": "Tue Dec 08 23:57:32 +0000 2015",
    "entities": {
        "hashtags": [],
        "symbols": [],
        "urls": [],
        "user_mentions": [
            {
                "id": 20793816,
                "id_str": "20793816",
                "indices": [
                    0,
                    7
                ],
                "name": "Amazon",
                "screen_name": "amazon"
            }
        ]
    },
    "favorite_count": 0,
    "favorited": false,
    "geo": null,
    "id": 674377300683583488,
    "id_str": "674377300683583488",
    "in_reply_to_screen_name": "amazon",
    "in_reply_to_status_id": null,
    "in_reply_to_status_id_str": null,
    "in_reply_to_user_id": 20793816,
    "in_reply_to_user_id_str": "20793816",
    "is_quote_status": false,
    "lang": "en",
    "metadata": {
        "iso_language_code": "en",
        "result_type": "recent"
    },
    "place": null,
    "retweet_count": 0,
    "retweeted": false,
    "source": "<a href=\"http://blackberry.com/twitter\" rel=\"nofollow\">Twitter for BlackBerry\u00ae</a>",
    "text": "@Amazon orders are shipping-out.And what happened?Today,I got the corniest thing that I ordered,1st.You kno you get all excited seeing boxes",
    "truncated": false,
    "user": {
        "contributors_enabled": false,
        "created_at": "Sat Mar 21 17:35:03 +0000 2009",
        "default_profile": false,
        "default_profile_image": false,
        "description": "Mother,Girlfriend,Bartender;SCORPIO:passionate,emotional,independent,energetic,determined,creative,persistent,intuitive,stubborn,secretive,vengeful,extreme...",
        "entities": {
            "description": {
                "urls": []
            }
        },
        "favourites_count": 2205,
        "follow_request_sent": false,
        "followers_count": 173,
        "following": false,
        "friends_count": 196,
        "geo_enabled": true,
        "has_extended_profile": false,
        "id": 25701096,
        "id_str": "25701096",
        "is_translation_enabled": false,
        "is_translator": false,
        "lang": "en",
        "listed_count": 3,
        "location": "ATL, GA",
        "name": "Mass Appeal",
        "notifications": false,
        "profile_background_color": "FF6699",
        "profile_background_image_url": "http://pbs.twimg.com/profile_background_images/253821572/PINK_1_.jpg",
        "profile_background_image_url_https": "https://pbs.twimg.com/profile_background_images/253821572/PINK_1_.jpg",
        "profile_background_tile": true,
        "profile_image_url": "http://pbs.twimg.com/profile_images/602644793743642624/ADtbKt3-_normal.jpg",
        "profile_image_url_https": "https://pbs.twimg.com/profile_images/602644793743642624/ADtbKt3-_normal.jpg",
        "profile_link_color": "B40B43",
        "profile_sidebar_border_color": "CC3385",
        "profile_sidebar_fill_color": "EB65A6",
        "profile_text_color": "362720",
        "profile_use_background_image": true,
        "protected": false,
        "screen_name": "1MassAppeal",
        "statuses_count": 3377,
        "time_zone": "Eastern Time (US & Canada)",
        "url": null,
        "utc_offset": -18000,
        "verified": false
    }
}