{
    "contributors": null,
    "coordinates": null,
    "created_at": "Sat Dec 05 00:27:09 +0000 2015",
    "entities": {
        "hashtags": [],
        "symbols": [],
        "urls": [],
        "user_mentions": [
            {
                "id": 62601419,
                "id_str": "62601419",
                "indices": [
                    0,
                    11
                ],
                "name": "Verizon Wireless CS",
                "screen_name": "VZWSupport"
            },
            {
                "id": 22342990,
                "id_str": "22342990",
                "indices": [
                    12,
                    19
                ],
                "name": "H",
                "screen_name": "Tark31"
            }
        ]
    },
    "favorite_count": 0,
    "favorited": false,
    "geo": null,
    "id": 672935203057324033,
    "id_str": "672935203057324033",
    "in_reply_to_screen_name": "VZWSupport",
    "in_reply_to_status_id": 672598818219827200,
    "in_reply_to_status_id_str": "672598818219827200",
    "in_reply_to_user_id": 62601419,
    "in_reply_to_user_id_str": "62601419",
    "is_quote_status": false,
    "lang": "en",
    "metadata": {
        "iso_language_code": "en",
        "result_type": "recent"
    },
    "place": null,
    "retweet_count": 0,
    "retweeted": false,
    "source": "<a href=\"http://twitter.com/#!/download/ipad\" rel=\"nofollow\">Twitter for iPad</a>",
    "text": "@VZWSupport @Tark31 Does adding this phone in anyway change my plan?",
    "truncated": false,
    "user": {
        "contributors_enabled": false,
        "created_at": "Mon Jan 14 04:20:13 +0000 2013",
        "default_profile": true,
        "default_profile_image": false,
        "description": "If we lose freedom here, there is no place to escape to. This is the last stand on Earth. - Ronald Reagan",
        "entities": {
            "description": {
                "urls": []
            }
        },
        "favourites_count": 1112,
        "follow_request_sent": false,
        "followers_count": 154,
        "following": false,
        "friends_count": 255,
        "geo_enabled": false,
        "has_extended_profile": false,
        "id": 1087991473,
        "id_str": "1087991473",
        "is_translation_enabled": false,
        "is_translator": false,
        "lang": "en",
        "listed_count": 3,
        "location": "",
        "name": "Jennifer",
        "notifications": false,
        "profile_background_color": "C0DEED",
        "profile_background_image_url": "http://abs.twimg.com/images/themes/theme1/bg.png",
        "profile_background_image_url_https": "https://abs.twimg.com/images/themes/theme1/bg.png",
        "profile_background_tile": false,
        "profile_banner_url": "https://pbs.twimg.com/profile_banners/1087991473/1358587553",
        "profile_image_url": "http://pbs.twimg.com/profile_images/624722404263227392/Ab-bxYqN_normal.jpg",
        "profile_image_url_https": "https://pbs.twimg.com/profile_images/624722404263227392/Ab-bxYqN_normal.jpg",
        "profile_link_color": "0084B4",
        "profile_sidebar_border_color": "C0DEED",
        "profile_sidebar_fill_color": "DDEEF6",
        "profile_text_color": "333333",
        "profile_use_background_image": true,
        "protected": false,
        "screen_name": "LibertyJennUSA",
        "statuses_count": 4100,
        "time_zone": null,
        "url": null,
        "utc_offset": null,
        "verified": false
    }
}