{
    "contributors": null,
    "coordinates": null,
    "created_at": "Sat Dec 05 15:28:10 +0000 2015",
    "entities": {
        "hashtags": [],
        "symbols": [],
        "urls": [],
        "user_mentions": [
            {
                "id": 18332190,
                "id_str": "18332190",
                "indices": [
                    0,
                    16
                ],
                "name": "British Airways",
                "screen_name": "British_Airways"
            }
        ]
    },
    "favorite_count": 0,
    "favorited": false,
    "geo": null,
    "id": 673161950126342145,
    "id_str": "673161950126342145",
    "in_reply_to_screen_name": "British_Airways",
    "in_reply_to_status_id": 673161444255494145,
    "in_reply_to_status_id_str": "673161444255494145",
    "in_reply_to_user_id": 18332190,
    "in_reply_to_user_id_str": "18332190",
    "is_quote_status": false,
    "lang": "en",
    "metadata": {
        "iso_language_code": "en",
        "result_type": "recent"
    },
    "place": null,
    "retweet_count": 0,
    "retweeted": false,
    "source": "<a href=\"http://twitter.com/download/iphone\" rel=\"nofollow\">Twitter for iPhone</a>",
    "text": "@British_Airways Thanks Lynn, all went smoothly afterwards. Not used to have to wait around prior to check in (much better at Heathrow).",
    "truncated": false,
    "user": {
        "contributors_enabled": false,
        "created_at": "Sat Sep 26 10:51:52 +0000 2009",
        "default_profile": false,
        "default_profile_image": false,
        "description": "Soft Tissue Therapist, working with private clients and at sports events around the UK: cycling and endurance running. Therapist to Loughton Manor FC.",
        "entities": {
            "description": {
                "urls": []
            },
            "url": {
                "urls": [
                    {
                        "display_url": "kaisersports.co.uk",
                        "expanded_url": "http://www.kaisersports.co.uk",
                        "indices": [
                            0,
                            23
                        ],
                        "url": "https://t.co/v4gF19uQkQ"
                    }
                ]
            }
        },
        "favourites_count": 58,
        "follow_request_sent": false,
        "followers_count": 272,
        "following": false,
        "friends_count": 724,
        "geo_enabled": true,
        "has_extended_profile": false,
        "id": 77448863,
        "id_str": "77448863",
        "is_translation_enabled": false,
        "is_translator": false,
        "lang": "en",
        "listed_count": 7,
        "location": "Buckinghamshire, UK",
        "name": "Marc Kaiser",
        "notifications": false,
        "profile_background_color": "FAF20A",
        "profile_background_image_url": "http://pbs.twimg.com/profile_background_images/237148851/KaiserSports_Logo_cropped.jpeg-for-web-normal.jpg",
        "profile_background_image_url_https": "https://pbs.twimg.com/profile_background_images/237148851/KaiserSports_Logo_cropped.jpeg-for-web-normal.jpg",
        "profile_background_tile": true,
        "profile_banner_url": "https://pbs.twimg.com/profile_banners/77448863/1393803712",
        "profile_image_url": "http://pbs.twimg.com/profile_images/664606294666567681/Lu4PovdU_normal.jpg",
        "profile_image_url_https": "https://pbs.twimg.com/profile_images/664606294666567681/Lu4PovdU_normal.jpg",
        "profile_link_color": "0084B4",
        "profile_sidebar_border_color": "000000",
        "profile_sidebar_fill_color": "DDEEF6",
        "profile_text_color": "333333",
        "profile_use_background_image": true,
        "protected": false,
        "screen_name": "kaisersports",
        "statuses_count": 2229,
        "time_zone": "London",
        "url": "https://t.co/v4gF19uQkQ",
        "utc_offset": 0,
        "verified": false
    }
}